{"data":{"meetupGroup":{"events":[{"name":"Lightning Round!","local_date":"2019-09-18","local_time":"17:30","venue":{"name":"YRC Worldwide","address_1":"10990 Roe Ave.","city":"Overland Park"},"link":"https://www.meetup.com/KansasCityJUG/events/264227992/","description":"<p>Have you always wanted to give a tech talk, but not sure that you can fill an hour? Are you passionate about what you do, but not sure how to share that passion with others? Would you like to show off a cool API that you found, or share your favorite IDE tools or shortcuts? This month's meetup will give you the perfect opportunity to take something that you want to talk about and present it! Talks range from 5-15 minutes, and we need YOU! Sign up to give a lightning talk here: <a href=\"https://forms.gle/o5sXdLoSBA1nXY476\" class=\"linkified\">https://forms.gle/o5sXdLoSBA1nXY476</a></p> "}]}}}